[
  {
    "is_a":false,
    "종목코드":"071050",
    "종목명":"한국금융지주",
    "시장":"KOSPI",
    "현재가":237000,
    "종합점수":72.2,
    "RSI":51.9,
    "이격도(%)":103.92,
    "ATR(%)":8.49,
    "ATR값":20123.0,
    "12개월수익률(%)":101.19,
    "거래대금(억)":578.1,
    "20일고가":263500,
    "수집시각":"2026-07-14 09:22"
  },
  {
    "is_a":false,
    "종목코드":"055550",
    "종목명":"신한지주",
    "시장":"KOSPI",
    "현재가":108600,
    "종합점수":66.2,
    "RSI":61.0,
    "이격도(%)":106.84,
    "ATR(%)":5.04,
    "ATR값":5474.0,
    "12개월수익률(%)":79.8,
    "거래대금(억)":1495.1,
    "20일고가":113300,
    "수집시각":"2026-07-14 09:22"
  },
  {
    "is_a":false,
    "종목코드":"316140",
    "종목명":"우리금융지주",
    "시장":"KOSPI",
    "현재가":31200,
    "종합점수":60.9,
    "RSI":53.7,
    "이격도(%)":102.59,
    "ATR(%)":4.89,
    "ATR값":1525.0,
    "12개월수익률(%)":52.2,
    "거래대금(억)":753.1,
    "20일고가":33700,
    "수집시각":"2026-07-14 09:22"
  },
  {
    "is_a":false,
    "종목코드":"086790",
    "종목명":"하나금융지주",
    "시장":"KOSPI",
    "현재가":132600,
    "종합점수":57.3,
    "RSI":63.0,
    "이격도(%)":109.07,
    "ATR(%)":4.89,
    "ATR값":6486.0,
    "12개월수익률(%)":70.88,
    "거래대금(억)":1763.4,
    "20일고가":137700,
    "수집시각":"2026-07-14 09:22"
  },
  {
    "is_a":false,
    "종목코드":"078930",
    "종목명":"GS",
    "시장":"KOSPI",
    "현재가":79500,
    "종합점수":53.9,
    "RSI":57.9,
    "이격도(%)":109.85,
    "ATR(%)":6.73,
    "ATR값":5352.0,
    "12개월수익률(%)":67.19,
    "거래대금(억)":486.1,
    "20일고가":86300,
    "수집시각":"2026-07-14 09:22"
  },
  {
    "is_a":false,
    "종목코드":"028670",
    "종목명":"팬오션",
    "시장":"KOSPI",
    "현재가":5240,
    "종합점수":50.1,
    "RSI":54.5,
    "이격도(%)":105.18,
    "ATR(%)":6.05,
    "ATR값":317.0,
    "12개월수익률(%)":40.86,
    "거래대금(억)":147.6,
    "20일고가":5570,
    "수집시각":"2026-07-14 09:22"
  },
  {
    "is_a":false,
    "종목코드":"021240",
    "종목명":"코웨이",
    "시장":"KOSPI",
    "현재가":91700,
    "종합점수":37.4,
    "RSI":51.4,
    "이격도(%)":101.29,
    "ATR(%)":6.07,
    "ATR값":5568.0,
    "12개월수익률(%)":0.0,
    "거래대금(억)":142.3,
    "20일고가":100500,
    "수집시각":"2026-07-14 09:22"
  },
  {
    "is_a":false,
    "종목코드":"207940",
    "종목명":"삼성바이오로직스",
    "시장":"KOSPI",
    "현재가":1400000,
    "종합점수":36.8,
    "RSI":52.0,
    "이격도(%)":101.59,
    "ATR(%)":5.15,
    "ATR값":72149.0,
    "12개월수익률(%)":-11.85,
    "거래대금(억)":638.6,
    "20일고가":1460000,
    "수집시각":"2026-07-14 09:22"
  },
  {
    "is_a":false,
    "종목코드":"214450",
    "종목명":"파마리서치",
    "시장":"KOSDAQ",
    "현재가":330500,
    "종합점수":34.5,
    "RSI":53.2,
    "이격도(%)":102.74,
    "ATR(%)":7.79,
    "ATR값":25738.0,
    "12개월수익률(%)":-34.03,
    "거래대금(억)":480.7,
    "20일고가":378500,
    "수집시각":"2026-07-14 09:22"
  },
  {
    "is_a":false,
    "종목코드":"323410",
    "종목명":"카카오뱅크",
    "시장":"KOSPI",
    "현재가":23300,
    "종합점수":26.6,
    "RSI":57.0,
    "이격도(%)":106.72,
    "ATR(%)":4.96,
    "ATR값":1155.0,
    "12개월수익률(%)":-20.07,
    "거래대금(억)":326.8,
    "20일고가":24600,
    "수집시각":"2026-07-14 09:22"
  }
]